[
    {
        "full_text": "0/100 Days of Illustration\n\nEver since I was a kid I wanted to learn to draw (traditionally) and paint (digitally) well. I used to do plenty for fun; I ended up honing my tech skills more than my art skills.\n\nTo illustrate my point, my goals are:",
        "created_at": "Sun Apr 30 21:27:05 +0000 2023",
        "id": "1652786677939666945",
        "media": false
    },
    {
        "full_text": "The first video said try to practice before learning how to do gesture drawing, so here are my first attempts.\n\nFirst pose was on all fours like WHY 😩🤣\n\nI suspect fewer lines, and less tentative ones, will come from practice; confidence.\n\n1/100 Days of Illustration https://t.co/XDImsQyUEZ",
        "created_at": "Mon May 01 21:06:00 +0000 2023",
        "id": "1653143758991511552",
        "media": "https://t.co/XDImsQyUEZ"
    },
    {
        "full_text": "I drew along with the video. The explanations helped considerably.\n\nI will try doing 2-3 sessions daily of 5-10 mins each to get enough practice.\n\nI have a feeling I'll draw for longer, though. I wasn't expecting this to be fun 💀\n\n2/100 Days of Illustration https://t.co/ZI6vm0cJj2",
        "created_at": "Tue May 02 12:30:15 +0000 2023",
        "id": "1653376354035851267",
        "media": "https://t.co/ZI6vm0cJj2"
    },
    {
        "full_text": "To think I need to do thousands of these 💀\n\nJust have to keep on going, and learning to improve all the while.\n\nThe Proko gesture critique video I watched today was p. insightful. I will try to take my time to do cleaner, single lines.\n\n3/100 Days of Illustration https://t.co/PsutZLSCPA",
        "created_at": "Wed May 03 21:35:23 +0000 2023",
        "id": "1653875926344650752",
        "media": "https://t.co/PsutZLSCPA"
    },
    {
        "full_text": "Learning to draw a torso as a bean to better capture gesture with simplified volume\n\nDefinitely struggling with seeing this well right now; MOAR PRACTICE!\n\n4/100 Days of Illustration https://t.co/a5LHgcqveL",
        "created_at": "Fri May 05 00:11:07 +0000 2023",
        "id": "1654277508634640384",
        "media": "https://t.co/a5LHgcqveL"
    },
    {
        "full_text": "More beans. More gestures.\n\nStarted videos on anatomy as well, but don't want to jump too far ahead too soon.\n\n5/100 Days of Illustration https://t.co/vIADVeRcGC",
        "created_at": "Fri May 05 20:47:07 +0000 2023",
        "id": "1654588555342106624",
        "media": "https://t.co/vIADVeRcGC"
    },
    {
        "full_text": "Today I started trying beans and gestures on my own; no guidance or drawing along. \n\nI'll get there.\n\nTravelled to Sheffield today so I don't have as much time as usual.\n\n6/100 Days of Illustration https://t.co/V0ufQw1EoN",
        "created_at": "Sat May 06 22:01:13 +0000 2023",
        "id": "1654969592475795460",
        "media": "https://t.co/V0ufQw1EoN"
    },
    {
        "full_text": "Mostly travelling today, so just these three took me longer to do - super tired rn xD Did watch a bunch of Love Life Drawing YT vids though!\n\nMinimum met. nn.\n\n7/100 Days of Illustration https://t.co/GB2Fgyx4ie",
        "created_at": "Mon May 08 00:28:21 +0000 2023",
        "id": "1655369009909444608",
        "media": "https://t.co/GB2Fgyx4ie"
    },
    {
        "full_text": "Starting to move onto volumes now.\n\nStill have to do daily gesture drawing as well~\n\n8/100 Days of Illustration https://t.co/Xhy88v1EV6",
        "created_at": "Mon May 08 22:32:22 +0000 2023",
        "id": "1655702209512759298",
        "media": "https://t.co/Xhy88v1EV6"
    },
    {
        "full_text": "Using volumes for objects.\n\nMaking a concerted effort to reduce the number of lines for my gesture drawings.\n\nChallenging. 😆\n\n9/100 Days of Illustration https://t.co/3sTeQBh8xq",
        "created_at": "Tue May 09 22:25:10 +0000 2023",
        "id": "1656062782033346561",
        "media": "https://t.co/3sTeQBh8xq"
    },
    {
        "full_text": "Travelling around London and might’ve caught something 😶 \n\nDead tired, so watched a video on anatomy landmarks and did a few gesture sketches.\n\n10/100 Days of Illustration https://t.co/gEAtThoyMz",
        "created_at": "Wed May 10 21:23:17 +0000 2023",
        "id": "1656409598029438977",
        "media": "https://t.co/gEAtThoyMz"
    },
    {
        "full_text": "Forgot to do the cube exercise xD I'll need to do more.\n\nTried a different pose generator and omg there are weird ones. Good. I need to train my eye-brain-hand movements.\n\nActually sick, so that's all for now! 😆 \n\n11/100 Days of Illustration https://t.co/IoZ0MXW5ZU",
        "created_at": "Thu May 11 19:10:14 +0000 2023",
        "id": "1656738501365202953",
        "media": "https://t.co/IoZ0MXW5ZU"
    },
    {
        "full_text": "Assignment was to sketch animals using volumes.\n\nI can do better, but it's okay for a sick Tabs ^^\n\n12/100 Days of Illustration https://t.co/co2LLxvOYR",
        "created_at": "Fri May 12 18:35:48 +0000 2023",
        "id": "1657092227229704217",
        "media": "https://t.co/co2LLxvOYR"
    },
    {
        "full_text": "Took a bunch of notes about landmarks, and then drew along with the video (top left).\n\nThen used the new gesture poses generator I'm using. Omg it gives me some weird ones 😆 Skipped a few views from underneath 🤣\n\n13/100 Days of Illustration https://t.co/v8GKD3SAv5",
        "created_at": "Sat May 13 23:57:38 +0000 2023",
        "id": "1657535604106592258",
        "media": "https://t.co/v8GKD3SAv5"
    },
    {
        "full_text": "Tried a different tutorial on constructing with landmarks. I hate it 🤣 Let me put in contours 😭\n\n14/100 Days of Illustration https://t.co/6JrG6MuuJ1",
        "created_at": "Sun May 14 20:25:32 +0000 2023",
        "id": "1657844618141089792",
        "media": "https://t.co/6JrG6MuuJ1"
    },
    {
        "full_text": "2/100 ribcages drawn 💀 Still recovering; low-energy day. Gestures are worse than my usual, too. \n\nAh, well. Tomorrow is another day. ^^\n\n15/100 Days of Illustration https://t.co/9HPmoEJbop",
        "created_at": "Mon May 15 19:40:08 +0000 2023",
        "id": "1658195581016080389",
        "media": "https://t.co/9HPmoEJbop"
    },
    {
        "full_text": "4/100 ribcages and some more gestures. Watched some videos in preparation for tomorrow; travelling back to the grandparents'. :D\n\n16/100 Days of Illustration https://t.co/919efFqO3i",
        "created_at": "Tue May 16 17:24:22 +0000 2023",
        "id": "1658523801334710277",
        "media": "https://t.co/919efFqO3i"
    },
    {
        "full_text": "Started on the robo-bean; followed along with the video.\n\nGestures today... Eh for ehffort. xD Too tired.\n\n17/100 Days of Illustration https://t.co/dFRjhEGC0H",
        "created_at": "Wed May 17 21:18:21 +0000 2023",
        "id": "1658945073655042048",
        "media": "https://t.co/dFRjhEGC0H"
    },
    {
        "full_text": "Was dead tired by number four, so called it a night.\n\nI should stop earlier 😆 \n\n18/100 Days of Illustration https://t.co/U8jW977BWs",
        "created_at": "Thu May 18 21:05:06 +0000 2023",
        "id": "1659304126910455808",
        "media": "https://t.co/U8jW977BWs"
    },
    {
        "full_text": "Started earlier today.\n\nGot more ribcages done thanks to friendly encouragement, and did better on the gesture drawings because I wasn't so damn tired.\n\nQuality of energy matters, apparently 😶\n\n19/100 Days of Illustration https://t.co/HjGg0Fp44C",
        "created_at": "Fri May 19 16:58:28 +0000 2023",
        "id": "1659604444290465810",
        "media": "https://t.co/HjGg0Fp44C"
    },
    {
        "full_text": "Spent all day packing, so... Tired once again, surprise surprise.\n\nDecided to take two figures slowly instead of doing more. I drew 5 ribcages today as well; the model isn't accurate so dunno how it looks from underneath xD That's okay though.\n\n20/100 Days of Illustration https://t.co/Y8acqZSADv",
        "created_at": "Sat May 20 22:42:31 +0000 2023",
        "id": "1660053416666644481",
        "media": "https://t.co/Y8acqZSADv"
    },
    {
        "full_text": "Today was a long day. You can see my brain starting off eh and then REALLY deteriorating with the last gesture xD\n\nIt seems my sense of proportion grows worse the more tired I become.\n\nUnhappy with today; however, this is what progress looks like. \n\n21/100 Days of Illustration https://t.co/aEq2NgTDeQ",
        "created_at": "Sun May 21 23:39:54 +0000 2023",
        "id": "1660430246170984448",
        "media": "https://t.co/aEq2NgTDeQ"
    },
    {
        "full_text": "Got to 40 rib cages! 60 left 💀 Going to try to do them over the next few days.\n\nI will indeed be sick of them soon xD\n\n22/100 Days of Illustration https://t.co/yhgfVWfgvm",
        "created_at": "Mon May 22 23:27:47 +0000 2023",
        "id": "1660789586233114631",
        "media": "https://t.co/yhgfVWfgvm"
    },
    {
        "full_text": "Literally all I managed on the first flight before I descended into pain. My ears 😭\n\nWhatevs. I spent most of the day travelling.\n\n23/100 Days of Illustration https://t.co/Ud3pDzbfrx",
        "created_at": "Wed May 24 09:39:15 +0000 2023",
        "id": "1661305853834838017",
        "media": "https://t.co/Ud3pDzbfrx"
    },
    {
        "full_text": "Forgot to make the post before I got onto the plane. Pleased I managed these before the final flight.\n\nEspecially compared to yesterday. 💀\n\n24/100 Days of Illustration https://t.co/mPfYaPInnu",
        "created_at": "Thu May 25 10:24:36 +0000 2023",
        "id": "1661679654644895744",
        "media": "https://t.co/mPfYaPInnu"
    },
    {
        "full_text": "WOO, nearly there! 70/100 ribcages done. Going to attempt the last 30 tomorrow 💀 Then I can finally return to gestures, the robo-bean, and learning about mannequins.\n\n25/100 Days of Illustration https://t.co/wRNVNzOV6Z",
        "created_at": "Thu May 25 15:53:48 +0000 2023",
        "id": "1661762501078573056",
        "media": "https://t.co/wRNVNzOV6Z"
    },
    {
        "full_text": "Spent today asleep, answering work emails, or with the bro so... Got 1/3 done of what I wanted. \n\nOne more day on these damn things 😬\n\n26/100 Days of Illustration https://t.co/G8pa06Z3o4",
        "created_at": "Fri May 26 13:30:25 +0000 2023",
        "id": "1662088801773326336",
        "media": "https://t.co/G8pa06Z3o4"
    },
    {
        "full_text": "100 Ribcages.\n\nDone.\n\nOnto other practice!\n\n27/100 Days of Illustration https://t.co/B06tPZuSIK",
        "created_at": "Sat May 27 09:44:22 +0000 2023",
        "id": "1662394304084713472",
        "media": "https://t.co/B06tPZuSIK"
    },
    {
        "full_text": "Slow brain day. \n\nReturned to my daily homework.\n\n28/100 Days of Illustration https://t.co/uhzbJ2KLQm",
        "created_at": "Sun May 28 16:58:48 +0000 2023",
        "id": "1662866020967788544",
        "media": "https://t.co/uhzbJ2KLQm"
    },
    {
        "full_text": "Started on mannequinsation videos. No drawing today; on a bus rn and the light annoys people xD \n\n29/100 Days of Illustration https://t.co/ElNScqSG9P",
        "created_at": "Mon May 29 13:21:21 +0000 2023",
        "id": "1663173683853279232",
        "media": "https://t.co/ElNScqSG9P"
    },
    {
        "full_text": "Gesture poses was all I had the energy for today.\n\nBack home in Australia now!\n\n30/100 Days of Illustration https://t.co/EiTkJRZEpB",
        "created_at": "Tue May 30 17:30:11 +0000 2023",
        "id": "1663598692669202435",
        "media": "https://t.co/EiTkJRZEpB"
    },
    {
        "full_text": "The robo-bean technique is difficult. And I can't imagine foreshortening under clothes, so I'll probs skip those going forward. \n\nMore practice until I get the twists right 😩🔥\n\n31/100 Days of Illustration https://t.co/KIAgiN9dn7",
        "created_at": "Wed May 31 14:20:36 +0000 2023",
        "id": "1663913370666385415",
        "media": "https://t.co/KIAgiN9dn7"
    },
    {
        "full_text": "Too tired to do well.\n\nI tried.\n\nTomorrow. 🙏🏽\n\n32/100 Days of Illustration https://t.co/ynW1tO4Xr3",
        "created_at": "Thu Jun 01 14:23:20 +0000 2023",
        "id": "1664276448973299715",
        "media": "https://t.co/ynW1tO4Xr3"
    },
    {
        "full_text": "I see improvement in my robo-beans. Not much, but better than yesterday.\n\nWOO!\n\n33/100 Days of Illustration https://t.co/8eHuThOsIL",
        "created_at": "Fri Jun 02 11:22:31 +0000 2023",
        "id": "1664593330653794304",
        "media": "https://t.co/8eHuThOsIL"
    },
    {
        "full_text": "I worked through critique videos today.\n\nI found a snippet on perspective particularly enjoyable and insightful.\n\nBest advice: details may make drawings look 'better', but mastery comes from solid foundations (structure, gesture, line quality, etc).\n\n34/100 Days of Illustration https://t.co/KxCsUAWGvZ",
        "created_at": "Sat Jun 03 10:32:05 +0000 2023",
        "id": "1664943025745690629",
        "media": "https://t.co/KxCsUAWGvZ"
    },
    {
        "full_text": "Draw-along mannequinsation today! Feels like better progress.\n\nI estimate about 4 more days until I feel ready to move along from the figure drawing courses into the Perspective I module.\n\n35/100 Days of Illustration https://t.co/lPoJl9BOqJ",
        "created_at": "Sun Jun 04 04:02:37 +0000 2023",
        "id": "1665207401794945024",
        "media": "https://t.co/lPoJl9BOqJ"
    },
    {
        "full_text": "I watched the shading videos, then tried to see how far I got with 30s gesture drawings.\n\nNot a massive amount of improvement, but definitely some since I started a month ago.\n\nOnward!\n\n36/100 Days of Illustration https://t.co/NtuqN4bMtv",
        "created_at": "Mon Jun 05 11:02:56 +0000 2023",
        "id": "1665675565700112387",
        "media": "https://t.co/NtuqN4bMtv"
    },
    {
        "full_text": "Two exercises.\n\nFirst one: Drew without looking at the page.\n\nSecond one: Looked at image for up to a minute, then drew for shit 30s from memory.\n\nBah 🤣 So bad, but the exercises are good.\n\n37/100 Days of Illustration https://t.co/5k7xX97gw4",
        "created_at": "Tue Jun 06 03:19:24 +0000 2023",
        "id": "1665921303424176131",
        "media": "https://t.co/5k7xX97gw4"
    },
    {
        "full_text": "I consumed a ton of content on gesture drawing; the FORCE method, and components of good gesture drawings. I won't be trying it all now; this skill needs to be developed iteratively.\n\nYay!! Onto Perspective I.\n\n38/100 Days of Illustration https://t.co/eJkuFeBs1x",
        "created_at": "Wed Jun 07 10:14:19 +0000 2023",
        "id": "1666388106180956161",
        "media": "https://t.co/eJkuFeBs1x"
    },
    {
        "full_text": "The course on perspective I'm working through was originally on VHS in the 90s 🙃\n\nIt's still great material that's absolutely applicable!\n\n39/100 Days of Illustration https://t.co/HK65fTCubx",
        "created_at": "Thu Jun 08 11:57:35 +0000 2023",
        "id": "1666776483732525057",
        "media": "https://t.co/HK65fTCubx"
    },
    {
        "full_text": "Worked through Drawabox Lesson 0.\n\nIt caused me to draw some parallels (*ahem*) and distinctions between how I treat coding/design/art things for hobbies vs. work.\n\nWork will never make me see those activities as unfun.\n\n40/100 Days of Illustration https://t.co/Ms92k7SJ2D",
        "created_at": "Fri Jun 09 12:21:54 +0000 2023",
        "id": "1667144989489627136",
        "media": "https://t.co/Ms92k7SJ2D"
    },
    {
        "full_text": "This is the first time it's properly sunk in that fluidity is more important than accuracy; removing the need to do any specific shape or figure will help focus on training this as a priority.\n\nLine quality COME TO MEEEEE~\n\n41/100 Days of Illustration https://t.co/vMghUXkzvL",
        "created_at": "Sat Jun 10 10:05:33 +0000 2023",
        "id": "1667473064769257474",
        "media": "https://t.co/vMghUXkzvL"
    },
    {
        "full_text": "Line exercises! Practicing drawing lines freehand; clearly I have more trouble with the longer ones.\n\nDrawing from the shoulder ain't easy starting out, especially with pulled neck + shoulder muscles 😬\n\nBut I diiiiiid it 😇 ~\n\n42/100 Days of Illustration https://t.co/viglFpjj7W",
        "created_at": "Sun Jun 11 11:21:24 +0000 2023",
        "id": "1667854541784776709",
        "media": "https://t.co/viglFpjj7W"
    },
    {
        "full_text": "Worked through the video and written content on ellipses and circles on Drawabox. I appreciate the way this is being taught; perhaps I just miss art classes.\n\nToo tired to get through the exercises so I'll get down to the three of them tomorrow.\n\n43/100 Days of Illustration https://t.co/Bw3jiQILQA",
        "created_at": "Mon Jun 12 09:37:51 +0000 2023",
        "id": "1668190871735640066",
        "media": "https://t.co/Bw3jiQILQA"
    },
    {
        "full_text": "I have five pages of exercises to do but the shoulder pain is *not* helping to Draw From The Shoulder. \n\nI'm going to cap it at a page a day while I work through other video content.\n\n44/100 Days of Illustration https://t.co/LVzFdsXocB",
        "created_at": "Tue Jun 13 03:09:46 +0000 2023",
        "id": "1668455594343419905",
        "media": "https://t.co/LVzFdsXocB"
    },
    {
        "full_text": "Pushing to my limit seems to increase recovery time, sooo I will just watch videos and take notes until I can draw from the shoulder properly. I finished the course intro today.\n\nOn the plus side - my fineliner pen arrived!\n\n45/100 Days of Illustration https://t.co/ZTsDT6EkYo",
        "created_at": "Wed Jun 14 13:53:42 +0000 2023",
        "id": "1668980030737711104",
        "media": "https://t.co/ZTsDT6EkYo"
    },
    {
        "full_text": "I'm familiar with these concepts already, but 5 minutes in he's already blowing my mind with the nuance in how to approach drawing 3D on a 2D surface.\n\nThis course is from 1994. Such a throwback to chalkboards and traditional classroom tech 😆\n\n46/100 Days of Illustration https://t.co/6hI8gqZTJJ",
        "created_at": "Thu Jun 15 01:10:28 +0000 2023",
        "id": "1669150346789392384",
        "media": "https://t.co/6hI8gqZTJJ"
    },
    {
        "full_text": "I was not expecting to get schooled on photography and vanishing points, but there you go.\n\nI appreciate the different levels of knowledge and the nuance in applying it to different contexts.\n\n47/100 Days of Illustration https://t.co/Sot0gt47AY",
        "created_at": "Fri Jun 16 11:29:29 +0000 2023",
        "id": "1669668512649052160",
        "media": "https://t.co/Sot0gt47AY"
    },
    {
        "full_text": "Key takeaway:\nWithin structure there is freedom.\n\nI've never been so excited to draw boxes.\n\n48/100 Days of Illustration https://t.co/HERSC7eNrV",
        "created_at": "Sat Jun 17 12:57:01 +0000 2023",
        "id": "1670052930307919872",
        "media": "https://t.co/HERSC7eNrV"
    },
    {
        "full_text": "Circle and ellipses are more difficult than right angles confirmed.\n\nThey seem so bitchy to handle 😭 But looking forward to getting better with them.\n\n49/100 Days of Illustration https://t.co/zIIYuz4mlD",
        "created_at": "Sun Jun 18 12:12:26 +0000 2023",
        "id": "1670404099354017794",
        "media": "https://t.co/zIIYuz4mlD"
    },
    {
        "full_text": "More videos, 'cause I still haven't recovered!\n\nEllipses are circles in space, and the axes used to draw them don't form the centre, which you get from checking the middle of a square. You get its angles from the lengths of the square similarly, too.\n\n50/100 Days of Illustration https://t.co/Ymc5ihUC0i",
        "created_at": "Mon Jun 19 13:03:17 +0000 2023",
        "id": "1670779285865635840",
        "media": "https://t.co/Ymc5ihUC0i"
    },
    {
        "full_text": "I know he says transcribing a speech is more incredible than being able to do this; it's still magic. This is magic - actionable magic, for once - but magic.\n\nI look forward to tearing my hair out and getting better at drawing things on spheres 😬\n\n51/100 Days of Illustration https://t.co/3fvuDk6XbI",
        "created_at": "Tue Jun 20 11:49:50 +0000 2023",
        "id": "1671123185356636162",
        "media": "https://t.co/3fvuDk6XbI"
    },
    {
        "full_text": "Vanishing points and vanishing traces; more magic, I tell you!\n\nIt's cool to finally understand how this stuff works though. I can't wait to apply all this to the drawabox 'draw for the fun of it' requirement, which has to be half of all drawing.\n\n52/100 Days of Illustration https://t.co/cyM8Ff0scl",
        "created_at": "Wed Jun 21 11:49:36 +0000 2023",
        "id": "1671485517052116992",
        "media": "https://t.co/cyM8Ff0scl"
    },
    {
        "full_text": "Vanishing points can become vanishing traces. P. cool. Learnt how to do inclined planes.\n\nThings make so much sense with the way sensei over here explains it 😭 \n\nI love that content 30 years old is still applicable - so used to tech moving non-stop.\n\n53/100 Days of Illustration https://t.co/NYyjdWgfme",
        "created_at": "Thu Jun 22 11:51:20 +0000 2023",
        "id": "1671848341129547776",
        "media": "https://t.co/NYyjdWgfme"
    },
    {
        "full_text": "Started on depth measuring. Apparently this is suddenly going to get complex as it pulls together the rest of the course, which has been 8 videos.\n\nTime to die xD\n\n54/100 Days of Illustration https://t.co/mO575e5e5u",
        "created_at": "Fri Jun 23 13:37:40 +0000 2023",
        "id": "1672237486138068993",
        "media": "https://t.co/mO575e5e5u"
    },
    {
        "full_text": "Today was one thing after another. But hey, today I did some socialisation OFFLINE so that's a plus.\n\nSpent a tiny bit of time on learning the next depth measuring technique; fairly intuitive if paying attention 💀\n\n55/100 Days of Illustration https://t.co/RALBSAi8PR",
        "created_at": "Sat Jun 24 14:23:44 +0000 2023",
        "id": "1672611469261963267",
        "media": "https://t.co/RALBSAi8PR"
    },
    {
        "full_text": "Vanishing Trace Diagonals! Third technique for measuring depth. Been wondering about this from the beginning; glad it's being address now.\n\nBeen coding through the weekend, so the last couple of videos will take a few days to get through xD\n\n56/100 Days of Illustration https://t.co/6Bu5J1bH7A",
        "created_at": "Sun Jun 25 09:39:11 +0000 2023",
        "id": "1672902248886849536",
        "media": "https://t.co/6Bu5J1bH7A"
    },
    {
        "full_text": "Learnt how to apply what I learnt yesterday to non-equal patterns (like windows on a building with gaps in-between them).\n\nALSO WATCHED SPIDER-MAN. \nOMGGGGGGGGG.\nAMAZING.\n\nThat made my week. :D\n\n57/100 Days of Illustration https://t.co/NrEuYNIddO",
        "created_at": "Mon Jun 26 12:20:51 +0000 2023",
        "id": "1673305318330343424",
        "media": "https://t.co/NrEuYNIddO"
    },
    {
        "full_text": "Finished the video earlier today so it won't be keeping me up tonight. Two left, and then I'll go back to drawing drills and see how my sprain tolerates it :D\n\nI look forward to an early bedtime so much it defeats the purpose a little bit 💀\n\n58/100 Days of Illustration https://t.co/JETfNCmJlU",
        "created_at": "Tue Jun 27 04:28:27 +0000 2023",
        "id": "1673548824688881664",
        "media": "https://t.co/JETfNCmJlU"
    },
    {
        "full_text": "More measuring magic✨\n\nI did my best to finish this video today, and so it's done.\n\nGot my work cut out for me on all fronts 😮‍💨 Back to drawing in a couple of days!\n\n59/100 Days of Illustration https://t.co/ToXVwDYb58",
        "created_at": "Wed Jun 28 10:39:00 +0000 2023",
        "id": "1674004464645332992",
        "media": "https://t.co/ToXVwDYb58"
    },
    {
        "full_text": "Gonna end up going through these a little more slowly because I need to learn about GSAP and ScrollTrigger in a few days 💀\n\nIt's the last video though; 1/4 of the way through and we're talking about plans and projections :D Familiar stuff, so far!\n\n60/100 Days of Illustration https://t.co/FCo5DH2jTr",
        "created_at": "Thu Jun 29 06:40:16 +0000 2023",
        "id": "1674306773891833857",
        "media": "https://t.co/FCo5DH2jTr"
    },
    {
        "full_text": "Well. That's the first time I've watched an object get flipped into perspective. V. cool! :D\n\nOnto GSAP and ScrollTrigger!~\n\n61/100 Days of Illustration https://t.co/gq6eKzE0HD",
        "created_at": "Fri Jun 30 02:46:19 +0000 2023",
        "id": "1674610287251689480",
        "media": "https://t.co/gq6eKzE0HD"
    },
    {
        "full_text": "Overloaded on GSAP and ScrollTrigger videos today, so only spared a few minutes for this 💀 \n\nTomorrow will likely be the same; essentially embarking on a repetition of the same points yesterday to drive the  point home.\n\nI'll make up for it later!\n\n62/100 Days of Illustration https://t.co/rcqROJzH7D",
        "created_at": "Sat Jul 01 12:53:53 +0000 2023",
        "id": "1675125573897822208",
        "media": "https://t.co/rcqROJzH7D"
    },
    {
        "full_text": "It is refreshing - so, so refreshing - to hear someone hammer home the point that there is value in going back to utter basics, re-inventing the wheel, doing things *manually*, and from scratch. Deep understanding ftw.\n\nFinished the video course. 🥳\n\n63/100 Days of Illustration https://t.co/hQMu9F5hZ4",
        "created_at": "Sun Jul 02 00:39:18 +0000 2023",
        "id": "1675303096673800192",
        "media": "https://t.co/hQMu9F5hZ4"
    },
    {
        "full_text": "Okay, we're back to drawing.\n\nI could just about tolerate some ellipses practice today. Tomorrow I may try to finish off this section and then move onto boxes.\n\n64/100 Days of Illustration https://t.co/u1Tno8T6zC",
        "created_at": "Mon Jul 03 12:31:28 +0000 2023",
        "id": "1675844705706459143",
        "media": "https://t.co/u1Tno8T6zC"
    },
    {
        "full_text": "Did the exercise. Not happy with it. But did the exercise.\n\nLate. Because I did it after streaming, which was a lovely distraction and a half helping someone figure out what they wanted to do with their IT/Computer Science education 🥳❤️\n\n65/100 Days of Illustration https://t.co/NqXaUN8fYV",
        "created_at": "Tue Jul 04 11:51:00 +0000 2023",
        "id": "1676196909550309377",
        "media": "https://t.co/NqXaUN8fYV"
    },
    {
        "full_text": "Moved onto learning about boxes. FINALLY. However, most of this perspective stuff seems straightforward after having been through that whole video course.\n\nRelief!\n\nI need to find my pen. I haven't even removed the lid and I've already lost it 🤣\n\n66/100 Days of Illustration https://t.co/qSqtUuhJc3",
        "created_at": "Wed Jul 05 13:01:13 +0000 2023",
        "id": "1676576971445391368",
        "media": "https://t.co/qSqtUuhJc3"
    },
    {
        "full_text": "Covered the last of the ellipses homework assignments, and continued with learning about boxes.\n\nI have a couple of sections of boxes to do before I can started on the homework and the dreaded 250 Boxes challenge.\n\n67/100 Days of Illustration https://t.co/mc0XBky2yr",
        "created_at": "Thu Jul 06 11:16:43 +0000 2023",
        "id": "1676913060928458752",
        "media": "https://t.co/mc0XBky2yr"
    },
    {
        "full_text": "The sheer GLEE I felt when there was some maths involved in explaining how art works 🤣\n\nThe gist: vanishing points accelerate as they move outwards.\n\n68/100 Days of Illustration https://t.co/BlmN77PTwB",
        "created_at": "Sat Jul 08 13:45:05 +0000 2023",
        "id": "1677675173091364864",
        "media": "https://t.co/BlmN77PTwB"
    },
    {
        "full_text": "Covered the last two chapters: Simplified Guidelines for 1, 2, and 3-point perspectives, foreshortening, horizon line (eye line/axis), distortion, and placing vanishing points.\n\nWhew. Next: drawing boxes.\n\n69 (nice) /100 Days of Illustration https://t.co/Wj0Ult4ZBI",
        "created_at": "Sat Jul 08 13:53:10 +0000 2023",
        "id": "1677677206770978819",
        "media": "https://t.co/Wj0Ult4ZBI"
    },
    {
        "full_text": "It took like 15-20 mins to get through the prep material for the first exercise, so I'll do the drawing tomorrow. ^^\n\nDidn't have much time for drawing today, but I DID sort out a menu bug. Productive Sunday :D :D\n\n70/100 Days of Illustration https://t.co/u5l8Jda2v0",
        "created_at": "Sun Jul 09 13:51:36 +0000 2023",
        "id": "1678039199067541505",
        "media": "https://t.co/u5l8Jda2v0"
    },
    {
        "full_text": "Not much today, but we are back to drawing. Let's goooo~~\n\nPerspective practice!\n\n71/100 Days of Illustration https://t.co/flHjOA7nYE",
        "created_at": "Mon Jul 10 14:09:47 +0000 2023",
        "id": "1678406162541080576",
        "media": "https://t.co/flHjOA7nYE"
    },
    {
        "full_text": "These boxes are not perfect but these boxes are mine :D\n\nWOO first task done!\n\n72/100 Days of Illustration https://t.co/edfBr0eldh",
        "created_at": "Tue Jul 11 07:18:15 +0000 2023",
        "id": "1678664985977982976",
        "media": "https://t.co/edfBr0eldh"
    },
    {
        "full_text": "I only had about 20 minutes to spare today (working towards a work deadline) so I covered the content explaining the next exercise, which I'll do tomorrow.\n\nWatched the videos and listened to the audio on the bus. We don't have time for breaks here 😆\n\n73/100 Days of Illustration https://t.co/vJM8GuIntl",
        "created_at": "Wed Jul 12 10:15:53 +0000 2023",
        "id": "1679072077255680001",
        "media": "https://t.co/vJM8GuIntl"
    },
    {
        "full_text": "I might've been up until 5 AM working so I went ahead and did some reading on the next exercise. HOW AM I SUPPOSED TO DRAW THIS??\n\nApparently: I'm not. At least not yet - I'm meant to go ahead and try it and suck at it. I'll improve over time.\n\n74/100 Days of Illustration https://t.co/zFBCGSDqwo",
        "created_at": "Fri Jul 14 04:58:01 +0000 2023",
        "id": "1679716857589399552",
        "media": "https://t.co/zFBCGSDqwo"
    },
    {
        "full_text": "Finished reading and listening to the page.\n\nYup, that's it.\n\nTomorrow: extended drawing session!\n\n75/100 Days of Illustration https://t.co/NDNdAKCM7T",
        "created_at": "Fri Jul 14 14:36:08 +0000 2023",
        "id": "1679862346242727936",
        "media": "https://t.co/NDNdAKCM7T"
    },
    {
        "full_text": "The thing I did for myself today was to finish the entire page in one go.\n\nKinda funny how the more I did the worse I seemed to get?? 🤣 The more extreme the perspective became the more I misjudged.\n\nA great exercise.\n\nTomorrow: the same thing! =_=\n\n76/100 Days of Illustration https://t.co/0gVAjsRYer",
        "created_at": "Sat Jul 15 14:22:23 +0000 2023",
        "id": "1680221275354984449",
        "media": "https://t.co/0gVAjsRYer"
    },
    {
        "full_text": "Long day.\n\nDecided to finish this page tonight anyway. I really wanna move on from this chapter and onto the gruelling 250 Box Challenge &gt;.&lt; Three more pages of exercises.\n\nMarginal improvement.\n\n77/100 Days of Illustration https://t.co/lcsQ8IpHQq",
        "created_at": "Sun Jul 16 12:57:37 +0000 2023",
        "id": "1680562331464466434",
        "media": "https://t.co/lcsQ8IpHQq"
    },
    {
        "full_text": "Prep for the next exercise. Again, because I forgot everything since the last time I looked at the content.\n\nI'll attempt this tomorrow. Wish me luck!\n\n78/100 Days of Illustration https://t.co/ajgSyro0AK",
        "created_at": "Mon Jul 17 15:12:01 +0000 2023",
        "id": "1680958541065240576",
        "media": "https://t.co/ajgSyro0AK"
    },
    {
        "full_text": "I neglected the part where we are supposed to draw for fun and do whatever we want.\n\nSo I drew for fun.\n\nBallpoint pen.\n\n79/100 Days of Illustration https://t.co/eJ3V0vmKi8",
        "created_at": "Tue Jul 18 11:11:14 +0000 2023",
        "id": "1681260331975462912",
        "media": "https://t.co/eJ3V0vmKi8"
    },
    {
        "full_text": "Tired, so prepped for another exercise.\n\nThis one is going to do my head in. Rotating boxes that increase in size to show depth. Aiyaaaa.\n\n80/100 Days of Illustration https://t.co/3MK1ov7uOA",
        "created_at": "Wed Jul 19 13:53:11 +0000 2023",
        "id": "1681663476115070977",
        "media": "https://t.co/3MK1ov7uOA"
    },
    {
        "full_text": "This is supposed to look more... Spherical. But whatever xD. Not as easy as it looks in the examples. And I finally started using my fine liner pen!\n\nThey deliberately chuck exercises at us that we're not able to do yet; into the fire, essentially.\n\n81/100 Days of Illustration https://t.co/NEibOyQhrt",
        "created_at": "Thu Jul 20 12:10:06 +0000 2023",
        "id": "1681999923141828608",
        "media": "https://t.co/NEibOyQhrt"
    },
    {
        "full_text": "More abject horror.\n\nI thought I could do two pages today, but this exercise is doing my head in xD\n\nSo one it is.\n\nOnto cleaning and coding!\n\n82/100 Days of Illustration https://t.co/BIszQeUcu5",
        "created_at": "Thu Jul 20 23:47:03 +0000 2023",
        "id": "1682175318201884673",
        "media": "https://t.co/BIszQeUcu5"
    },
    {
        "full_text": "Worse in some ways because I forgot some instructions and didn't put in as much effort as I could have done.\n\nHowever: I see some improvement in the speed it takes for me to make a judgement call.\n\nMy brain is actually processing convergence.\n\n83/100 Days of Illustration https://t.co/2M7XH1HapX",
        "created_at": "Sat Jul 22 01:02:48 +0000 2023",
        "id": "1682556768931708928",
        "media": "https://t.co/2M7XH1HapX"
    },
    {
        "full_text": "Going through the prep alone took me like half an hour; that's all I had the energy for today on top of work and other stuff.\n\nTime to attempt to finish packing up the art cupboard ^^\n\n84/100 Days of Illustration https://t.co/T0uSfR5Y5H",
        "created_at": "Sun Jul 23 09:03:13 +0000 2023",
        "id": "1683040055500341249",
        "media": "https://t.co/T0uSfR5Y5H"
    },
    {
        "full_text": "I feel so called out. They've gone and described a similar journey to us finding that free art syllabus online and taking it from there xD Whelp.\n\nTotally knackered; spent today working and cleaning 😴 \n\n85/100 Days of Illustration https://t.co/d9J3HJ15Yw",
        "created_at": "Mon Jul 24 14:48:56 +0000 2023",
        "id": "1683489445205475328",
        "media": "https://t.co/d9J3HJ15Yw"
    },
    {
        "full_text": "Watched a tutorial on drawing chibis because I damn well felt like it.\n\nThat was yesterday. Was too tired to post. xD\n\nBUT HEY THE ART CUPBOARD IS (99%) DOOONEEE~\n\n86/100 Days of Illustration https://t.co/BDOGCvJ2Et",
        "created_at": "Wed Jul 26 12:44:48 +0000 2023",
        "id": "1684182984273072129",
        "media": "https://t.co/BDOGCvJ2Et"
    },
    {
        "full_text": "I followed another tutorial from the CutieDrawing YT channel 💀\n\nWe're supposed to do drawing for fun, so... Too bad so sad, I've always wanted to make cute chibis 🤣🤣\n\n87/100 Days of Illustration https://t.co/grijpdS1aH",
        "created_at": "Wed Jul 26 13:07:58 +0000 2023",
        "id": "1684188811688017922",
        "media": "https://t.co/grijpdS1aH"
    },
    {
        "full_text": "I drew it in pencil and then went over it in pen to see what that would do.\n\nFollowed another tutorial for the sitting pose. I could probs look at general poses and try to draw them in the chibi-style, tbh.\n\nSome of the tutorials are... Eh. &gt;_&gt;\n\n88/100 Days of Illustration https://t.co/mX9f4O0z6Z",
        "created_at": "Thu Jul 27 08:27:57 +0000 2023",
        "id": "1684480734273363971",
        "media": "https://t.co/mX9f4O0z6Z"
    },
    {
        "full_text": "Today is the day  in which I learn to wait before ink dries 💀\n\nI will be practicing chibis for the foreseeable future in-between my drawing challenges. They're fun! And I'd like to draw my own emotes for Twitch anyway.\n\n89/100 Days of Illustration https://t.co/02a56rz40W",
        "created_at": "Fri Jul 28 00:04:11 +0000 2023",
        "id": "1684716343772491776",
        "media": "https://t.co/02a56rz40W"
    },
    {
        "full_text": "I watched a video and found I was critical of ability based on process and technique; I'm used to learning from industry experts who hammer home certain points.\n\nThere was still something to learn, and I appreciate their sharing it; they're great at what they do. I just need to… https://t.co/Gbz0om6Apf",
        "created_at": "Sun Jul 30 06:17:14 +0000 2023",
        "id": "1685534999653826560",
        "media": "https://t.co/Gbz0om6Apf"
    },
    {
        "full_text": "And today I learn about how colouring with ink in the way I did loses detail. And then I overcompensate elsewhere. Woo!~\n\nI am meant to be doing 50% drawing for fun, and 50% doing the challenges - but still nowhere near evening that out xD\n\n91/100 Days of Illustration https://t.co/US68micWGm",
        "created_at": "Sun Jul 30 14:19:08 +0000 2023",
        "id": "1685656275181510656",
        "media": "https://t.co/US68micWGm"
    },
    {
        "full_text": "Hair and expression practice; still experimenting  to decide what I like.\n\nI was explaining how to erase on paper in just one direction only, and then ofc the second after I'm done I make that very mistake and crinkle the paper 💀\n\n92/100 Days of Illustration https://t.co/rDQSqgWU3u",
        "created_at": "Mon Jul 31 09:28:56 +0000 2023",
        "id": "1685945630412468224",
        "media": "https://t.co/rDQSqgWU3u"
    },
    {
        "full_text": "Watched a video using SAI to see sort of how the program works. I'll need to pick something soon enough.\n\nI just have to find the damn tablet pens 💀Got no idea where they are.\n\n93/100 Days of Illustration https://t.co/5jtgIxKSJg",
        "created_at": "Tue Aug 01 11:50:15 +0000 2023",
        "id": "1686343581190254594",
        "media": "https://t.co/5jtgIxKSJg"
    },
    {
        "full_text": "Watched this video on finding my art style; created the mood board and started filling it.\n\nAlso, f typing with long nails idk how people wear these without getting annoyed af xD Were they originally chicken-pecking the keyboard??\n\n94/100 Days of Illustration https://t.co/Lu8ixIftKV",
        "created_at": "Wed Aug 02 14:53:24 +0000 2023",
        "id": "1686752061604397059",
        "media": "https://t.co/Lu8ixIftKV"
    },
    {
        "full_text": "Ended up with 40 pins on my board so far. This is going to take me time to build and curate.\n\nSo far it seems like my style is mostly 'drama'; in the form of lighting, contrasting palettes, moody expressions, and so on.\n\n95/100 Days of Illustration https://t.co/tt910cJ7hK",
        "created_at": "Thu Aug 03 12:38:36 +0000 2023",
        "id": "1687080525310435333",
        "media": "https://t.co/tt910cJ7hK"
    },
    {
        "full_text": "Prep for box bootcamp tomorrow; watched a video explaining mistakes people make, and a critique of some homework.\n\nWahhh. 250 boxes incoming. Wish me luck~~\n\n96/100 Days of Illustration https://t.co/jg6EISBYxb",
        "created_at": "Fri Aug 04 12:49:43 +0000 2023",
        "id": "1687445709988249600",
        "media": "https://t.co/jg6EISBYxb"
    },
    {
        "full_text": "Box bootcamp begins. I've already fked up at least two of them 😆\n\n5 down, 245 to go.\n\n💀\n\n97/100 Days of Illustration https://t.co/C5idEUdhC3",
        "created_at": "Sat Aug 05 12:00:06 +0000 2023",
        "id": "1687795614665609216",
        "media": "https://t.co/C5idEUdhC3"
    },
    {
        "full_text": "Hooo lordy are some of these cubes wonky!\n\nGood thing I have to do 250 of them. 💀\n\n98/100 Days of Illustration https://t.co/h30b8LINz5",
        "created_at": "Sun Aug 06 13:10:42 +0000 2023",
        "id": "1688175768336232450",
        "media": "https://t.co/h30b8LINz5"
    },
    {
        "full_text": "I still see mistakes even before I've extended the lines to the vanishing points; the margin of error is slowly decreasing though, so that's a good sign.\n\nI draw these all freehand with no reference.\n\n99/100 Days of Illustration https://t.co/rgCeCVl9ki",
        "created_at": "Mon Aug 07 13:57:39 +0000 2023",
        "id": "1688549970952261632",
        "media": "https://t.co/rgCeCVl9ki"
    },
    {
        "full_text": "Whew.\n\nMy lines are starting to conveeergeeee. Exciting!\n\nI managed to get to 25 boxes; it's so much effort, omg. I will continue so my progress doesn't decay, though I'll be more sporadic after the boxes.\n\nSee you on Sep 1st for 100 Days of Health! :D\n\n100/100 Days of… https://t.co/Ff4IDlzCyl",
        "created_at": "Tue Aug 08 11:31:12 +0000 2023",
        "id": "1688875503997132800",
        "media": "https://t.co/Ff4IDlzCyl"
    }
]